chaosswarm/__init__.py
chaosswarm/actions.py
chaosswarm/probes.py
chaostoolkit_docker_swarm-0.3.0.dist-info/LICENSE
chaostoolkit_docker_swarm-0.3.0.dist-info/METADATA
chaostoolkit_docker_swarm-0.3.0.dist-info/WHEEL
chaostoolkit_docker_swarm-0.3.0.dist-info/top_level.txt
chaostoolkit_docker_swarm-0.3.0.dist-info/RECORD
