Metadata-Version: 2.1
Name: chaostoolkit-docker-swarm
Version: 0.3.0
Summary: Chaos Toolkit Extension for Docker Swarm
Home-page: https://github.com/bittrance/chaostoolkit-docker-swarm/
Author: Quest
Author-email: quest@lysator.liu.se
License: Apache License Version 2.0
Platform: UNKNOWN
Classifier: Development Status :: 2 - Pre-Alpha
Classifier: Intended Audience :: Developers
Classifier: Operating System :: OS Independent
Classifier: License :: Freely Distributable
Classifier: License :: OSI Approved :: Apache Software License
Classifier: Programming Language :: Python
Classifier: Programming Language :: Python :: 3
Classifier: Programming Language :: Python :: 3.5
Classifier: Programming Language :: Python :: 3.8
Classifier: Programming Language :: Python :: Implementation
Classifier: Programming Language :: Python :: Implementation :: CPython
Requires-Python: >=3.5.*
Requires-Dist: chaostoolkit-lib (>=0.8.2)
Requires-Dist: docker
Requires-Dist: pycodestyle
